{
	"animations": [
		{
			"offsets": [
				180,
				-32
			],
			"loop": false,
			"fps": 24,
			"anim": "idle",
			"indices": [],
			"name": "Idle"
		},
		{
			"offsets": [
				180,
				-146
			],
			"loop": false,
			"fps": 24,
			"anim": "singDOWN",
			"indices": [],
			"name": "Down"
		},
		{
			"offsets": [
				180,
				-60
			],
			"loop": false,
			"fps": 24,
			"anim": "singUP",
			"indices": [],
			"name": "Up"
		},
		{
			"loop": false,
			"offsets": [
				178,
				-35
			],
			"anim": "singLEFT",
			"fps": 24,
			"name": "Right",
			"indices": []
		},
		{
			"loop": false,
			"offsets": [
				181,
				-87
			],
			"anim": "singRIGHT",
			"fps": 24,
			"name": "Left",
			"indices": []
		}
	],
	"no_antialiasing": false,
	"image": "characters/Bodoque",
	"position": [
		0,
		0
	],
	"healthicon": "bodoque",
	"flip_x": false,
	"healthbar_colors": [
		203,
		17,
		27
	],
	"camera_position": [
		-330,
		0
	],
	"sing_duration": 4,
	"scale": 1
}